ailab/__init__.py
ailab/answer.py
ailab/command.py
ailab/main.py
insutance/__init__.py
insutance/answer.py
insutance/command.py
insutance/main.py
dnc_scheduler-0.0.1.dist-info/METADATA
dnc_scheduler-0.0.1.dist-info/WHEEL
dnc_scheduler-0.0.1.dist-info/entry_points.txt
dnc_scheduler-0.0.1.dist-info/top_level.txt
dnc_scheduler-0.0.1.dist-info/RECORD
