Metadata-Version: 2.1
Name: dnc-scheduler
Version: 0.0.1
Summary: Hey DnC! Who are you?
Home-page: https://github.com/dnclouis/dnc-scheduler
Author: hanjoo.moon
Author-email: moonhj3117@gmail.com
License: UNKNOWN
Platform: UNKNOWN
Requires-Python: >= 3.8
